km3flux/__init__.py
km3flux/aeff.py
km3flux/data.py
km3flux/flux.py
km3flux/version.py
km3flux/weights.py
km3flux/data/Histo-GC-AllMass-AllCh-CMSSM.h5
km3flux/data/Histo-Sun-AllMass-AllCh-CMSSM.h5
km3flux/data/all.csv
km3flux/data/cirelli_gc.h5
km3flux/data/frj-ally-20-01-solmin.txt
km3flux/data/gc_spectra.h5
km3flux/data/honda2015_frejus_solarmin.h5
km3flux/data/parse.py
km3flux/data/parse_av.py
km3flux/data/ppflux_to_usable.py
km3flux/data/sun_spectra.h5
km3flux/data/test_dmf.py
km3flux/data/wimpsim_1d.h5
km3flux/data/read_cirelli/AtProductionNoEW_neutrinos_mu.dat
km3flux/data/read_cirelli/AtProduction_neutrinos_mu.dat
km3flux/data/read_cirelli/GC_neutrinos_e.dat
km3flux/data/read_cirelli/GC_neutrinos_mu.dat
km3flux/data/read_cirelli/GC_neutrinos_tau.dat
km3flux/data/read_cirelli/parse cirelli tables.ipynb
km3flux/data/split_raw/cos_-0.1_0.0.csv
km3flux/data/split_raw/cos_-0.2_-0.1.csv
km3flux/data/split_raw/cos_-0.3_-0.2.csv
km3flux/data/split_raw/cos_-0.4_-0.3.csv
km3flux/data/split_raw/cos_-0.5_-0.4.csv
km3flux/data/split_raw/cos_-0.6_-0.5.csv
km3flux/data/split_raw/cos_-0.7_-0.6.csv
km3flux/data/split_raw/cos_-0.8_-0.7.csv
km3flux/data/split_raw/cos_-0.9_-0.8.csv
km3flux/data/split_raw/cos_-1.0_-0.9.csv
km3flux/data/split_raw/cos_0.0_0.1.csv
km3flux/data/split_raw/cos_0.1_0.2.csv
km3flux/data/split_raw/cos_0.2_0.3.csv
km3flux/data/split_raw/cos_0.3_0.4.csv
km3flux/data/split_raw/cos_0.4_0.5.csv
km3flux/data/split_raw/cos_0.5_0.6.csv
km3flux/data/split_raw/cos_0.6_0.7.csv
km3flux/data/split_raw/cos_0.7_0.8.csv
km3flux/data/split_raw/cos_0.8_0.9.csv
km3flux/data/split_raw/cos_0.9_1.0.csv
km3flux/data/wimpsim/Read Wimpsim Table.ipynb
km3flux/data/wimpsim/sep_norm.svg
km3flux/data/wimpsim/spectra_norm.svg
km3flux/data/wimpsim/data/we-m10-ch1-su-1D-diff-f1.dat
km3flux/data/wimpsim/data/we-m10-ch1-su-2D-diff-f1.dat
km3flux/data/wimpsim/data/we-m10-ch11-su-1D-diff-f1.dat
km3flux/data/wimpsim/data/we-m10-ch11-su-2D-diff-f1.dat
km3flux-1.0.3.dist-info/LICENSE
km3flux-1.0.3.dist-info/METADATA
km3flux-1.0.3.dist-info/WHEEL
km3flux-1.0.3.dist-info/top_level.txt
km3flux-1.0.3.dist-info/RECORD
