Metadata-Version: 2.1
Name: km3flux
Version: 1.0.3
Summary: Neutrino fluxes
Home-page: http://git.km3net.de/km3py/km3flux
Author: Moritz Lotze
Author-email: mlotze@km3net.de
License: UNKNOWN
Platform: any
Classifier: Intended Audience :: Developers
Classifier: Intended Audience :: Science/Research
Classifier: Programming Language :: Python
Requires-Python: >=3.6
Requires-Dist: docopt
Requires-Dist: h5py
Requires-Dist: matplotlib (>=2.0)
Requires-Dist: mock
Requires-Dist: numpy
Requires-Dist: pandas
Requires-Dist: scipy
Requires-Dist: tables
Provides-Extra: dev
Requires-Dist: black (==21.9b0) ; extra == 'dev'
Requires-Dist: ipython ; extra == 'dev'
Requires-Dist: matplotlib ; extra == 'dev'
Requires-Dist: memory-profiler ; extra == 'dev'
Requires-Dist: mock ; extra == 'dev'
Requires-Dist: numpydoc ; extra == 'dev'
Requires-Dist: pillow ; extra == 'dev'
Requires-Dist: pytest ; extra == 'dev'
Requires-Dist: pytest-cov ; extra == 'dev'
Requires-Dist: pytest-flake8 ; extra == 'dev'
Requires-Dist: pytest-pylint ; extra == 'dev'
Requires-Dist: pytest-watch ; extra == 'dev'
Requires-Dist: scipy ; extra == 'dev'
Requires-Dist: sphinx ; extra == 'dev'
Requires-Dist: sphinx-autoapi ; extra == 'dev'
Requires-Dist: sphinx-gallery (>=0.1.12) ; extra == 'dev'
Requires-Dist: sphinx-rtd-theme ; extra == 'dev'
Requires-Dist: sphinxcontrib-napoleon ; extra == 'dev'
Requires-Dist: sphinxcontrib-programoutput ; extra == 'dev'
Requires-Dist: sphinxcontrib-versioning ; extra == 'dev'
Requires-Dist: sphinxcontrib-websupport ; extra == 'dev'
Requires-Dist: twine ; extra == 'dev'
Requires-Dist: wheel ; extra == 'dev'
